mcos/__init__.py
mcos/covariance_transformer.py
mcos/error_estimator.py
mcos/mcos.py
mcos/observation_simulator.py
mcos/optimizer.py
mcos-0.1.0.dist-info/LICENSE
mcos-0.1.0.dist-info/METADATA
mcos-0.1.0.dist-info/WHEEL
mcos-0.1.0.dist-info/top_level.txt
mcos-0.1.0.dist-info/RECORD
